[{"id":712841,"name":"BELO POLJE","cadastre_type":3,"updated_at":{"seconds":1626166200}},{"id":712850,"name":"BERŠIĆI","cadastre_type":3,"updated_at":{"seconds":1626166200}},{"id":712868,"name":"BRAJIĆI","cadastre_type":3,"updated_at":{"seconds":1626166200}},{"id":712876,"name":"BREZNA","cadastre_type":3,"updated_at":{"seconds":1626166200}},{"id":712884,"name":"BRUSNICA","cadastre_type":3,"updated_at":{"seconds":1626166200}},{"id":712892,"name":"VELEREČ","cadastre_type":3,"updated_at":{"seconds":1626166200}},{"id":712906,"name":"VRAĆEVŠNICA","cadastre_type":3,"updated_at":{"seconds":1626166200}},{"id":712914,"name":"VRNČANI","cadastre_type":3,"updated_at":{"seconds":1626166200}},{"id":712922,"name":"GORNJI BANJANI","cadastre_type":3,"updated_at":{"seconds":1626166200}},{"id":712949,"name":"GORNJI BRANETIĆI","cadastre_type":3,"updated_at":{"seconds":1626166200}},{"id":712957,"name":"GORNJA VRBAVA","cadastre_type":3,"updated_at":{"seconds":1626166200}},{"id":712965,"name":"GORNJI MILANOVAC","cadastre_type":3,"updated_at":{"seconds":1626166200}},{"id":712973,"name":"GORNJA CRNUĆA","cadastre_type":3,"updated_at":{"seconds":1626166200}},{"id":712981,"name":"GRABOVICA","cadastre_type":3,"updated_at":{"seconds":1626166200}},{"id":712990,"name":"DONJA VRBAVA","cadastre_type":3,"updated_at":{"seconds":1626166200}},{"id":713007,"name":"DONJI BRANETIĆI","cadastre_type":3,"updated_at":{"seconds":1626166200}},{"id":713015,"name":"DONJA CRNUĆA","cadastre_type":3,"updated_at":{"seconds":1626166200}},{"id":713023,"name":"DRENOVA","cadastre_type":3,"updated_at":{"seconds":1626166200}},{"id":713031,"name":"JABLANICA","cadastre_type":3,"updated_at":{"seconds":1626166200}},{"id":713040,"name":"KALIMANIĆI","cadastre_type":3,"updated_at":{"seconds":1626166200}},{"id":713058,"name":"KLATIČEVO","cadastre_type":3,"updated_at":{"seconds":1626166200}},{"id":713066,"name":"KOŠTUNIĆI","cadastre_type":3,"updated_at":{"seconds":1626166200}},{"id":713074,"name":"LEUŠIĆI","cadastre_type":3,"updated_at":{"seconds":1626166200}},{"id":713082,"name":"LIPOVAC","cadastre_type":3,"updated_at":{"seconds":1626166200}},{"id":713104,"name":"LOZANJ","cadastre_type":3,"updated_at":{"seconds":1626166200}},{"id":713112,"name":"LOČEVCI","cadastre_type":3,"updated_at":{"seconds":1626166200}},{"id":713139,"name":"LUNJEVICA","cadastre_type":3,"updated_at":{"seconds":1626166200}},{"id":713147,"name":"LJEVAJA","cadastre_type":3,"updated_at":{"seconds":1626166200}},{"id":713155,"name":"LJUTOVNICA","cadastre_type":3,"updated_at":{"seconds":1626166200}},{"id":713163,"name":"MAJDAN","cadastre_type":3,"updated_at":{"seconds":1626166200}},{"id":713171,"name":"NAKUČANI","cadastre_type":3,"updated_at":{"seconds":1626166200}},{"id":713180,"name":"NEVADE","cadastre_type":3,"updated_at":{"seconds":1626166200}},{"id":713198,"name":"OZREM","cadastre_type":3,"updated_at":{"seconds":1626166200}},{"id":713201,"name":"POLOM","cadastre_type":3,"updated_at":{"seconds":1626166200}},{"id":713210,"name":"PRANJANI","cadastre_type":3,"updated_at":{"seconds":1626166200}},{"id":713228,"name":"PRNJAVOR","cadastre_type":3,"updated_at":{"seconds":1626166200}},{"id":713236,"name":"SVRAČKOVCI","cadastre_type":3,"updated_at":{"seconds":1626166200}},{"id":713244,"name":"SEMEDRAŽ","cadastre_type":3,"updated_at":{"seconds":1626166200}},{"id":713252,"name":"SINOŠEVIĆI","cadastre_type":3,"updated_at":{"seconds":1626166200}},{"id":713279,"name":"SREZOJEVCI","cadastre_type":3,"updated_at":{"seconds":1626166200}},{"id":713287,"name":"TAKOVO","cadastre_type":3,"updated_at":{"seconds":1626166200}},{"id":713295,"name":"TEOČIN","cadastre_type":3,"updated_at":{"seconds":1626166200}},{"id":713309,"name":"ŠARANI","cadastre_type":3,"updated_at":{"seconds":1626166200}},{"id":726966,"name":"BOLJKOVCI","cadastre_type":3,"updated_at":{"seconds":1626166200}},{"id":727008,"name":"BREZOVICA","cadastre_type":3,"updated_at":{"seconds":1626166200}},{"id":727059,"name":"DAVIDOVICA","cadastre_type":3,"updated_at":{"seconds":1626166200}},{"id":727083,"name":"DRAGOLJ","cadastre_type":3,"updated_at":{"seconds":1626166200}},{"id":727105,"name":"ZAGRAĐE","cadastre_type":3,"updated_at":{"seconds":1626166200}},{"id":727156,"name":"KRIVA REKA","cadastre_type":3,"updated_at":{"seconds":1626166200}},{"id":727237,"name":"MUTANJ","cadastre_type":3,"updated_at":{"seconds":1626166200}},{"id":727253,"name":"RELJINCI","cadastre_type":3,"updated_at":{"seconds":1626166200}},{"id":727261,"name":"RUDNIK","cadastre_type":3,"updated_at":{"seconds":1626166200}},{"id":727270,"name":"RUČIĆI","cadastre_type":3,"updated_at":{"seconds":1626166200}},{"id":727288,"name":"TRUDELJ","cadastre_type":3,"updated_at":{"seconds":1626166200}},{"id":727296,"name":"UGRINOVCI","cadastre_type":3,"updated_at":{"seconds":1626166200}},{"id":727300,"name":"CEROVA","cadastre_type":3,"updated_at":{"seconds":1626166200}},{"id":727318,"name":"ŠILOPAJ","cadastre_type":3,"updated_at":{"seconds":1626166200}},{"id":743232,"name":"BOGDANICA","cadastre_type":3,"updated_at":{"seconds":1626166200}},{"id":743305,"name":"GOJNA GORA","cadastre_type":3,"updated_at":{"seconds":1626166200}},{"id":743364,"name":"DRUŽETIĆI","cadastre_type":3,"updated_at":{"seconds":1626166200}},{"id":744328,"name":"BRĐANI","cadastre_type":3,"updated_at":{"seconds":1626166200}}]
